ionics_fits/MLE.py
ionics_fits/__init__.py
ionics_fits/binomial.py
ionics_fits/common.py
ionics_fits/errorbars.py
ionics_fits/models/__init__.py
ionics_fits/models/benchmarking.py
ionics_fits/models/cone.py
ionics_fits/models/exponential.py
ionics_fits/models/gaussian.py
ionics_fits/models/heuristics.py
ionics_fits/models/laser_rabi.py
ionics_fits/models/lorentzian.py
ionics_fits/models/molmer_sorensen.py
ionics_fits/models/multi_x.py
ionics_fits/models/polynomial.py
ionics_fits/models/quantum_phys.py
ionics_fits/models/rabi.py
ionics_fits/models/ramsey.py
ionics_fits/models/rectangle.py
ionics_fits/models/sigmoid.py
ionics_fits/models/sinc.py
ionics_fits/models/sinusoid.py
ionics_fits/models/transformations/__init__.py
ionics_fits/models/transformations/aggregate_model.py
ionics_fits/models/transformations/mapped_model.py
ionics_fits/models/transformations/model_2d.py
ionics_fits/models/transformations/reparametrized_model.py
ionics_fits/models/transformations/repeated_model.py
ionics_fits/models/transformations/scaled_model.py
ionics_fits/models/triangle.py
ionics_fits/models/utils.py
ionics_fits/normal.py
ionics_fits/utils.py
ionics_fits/validators.py
ionics_fits-1.3.17.dist-info/METADATA
ionics_fits-1.3.17.dist-info/LICENSE
ionics_fits-1.3.17.dist-info/WHEEL
ionics_fits-1.3.17.dist-info/RECORD
