Metadata-Version: 2.1
Name: ionics-fits
Version: 1.3.17
Summary: Lightweight Python data fitting library with an emphasis on AMO/Quantum Information
Author: hartytp
Author-email: thomas.peter.harty@gmail.com
Requires-Python: >=3.10,<4.0
Classifier: Programming Language :: Python :: 3
Classifier: Programming Language :: Python :: 3.10
Classifier: Programming Language :: Python :: 3.11
Requires-Dist: numpy (>=1.21.2,<3.0)
Requires-Dist: scipy (>=1.7.1,<2.0.0)
Requires-Dist: statsmodels (>=0.14.0,<0.15.0)
